riemann_keys/__init__.py
riemann_keys/base58.py
riemann_keys/bip39.py
riemann_keys/hdkey.py
riemann_keys/utils.py
riemann_keys/data/__init__.py
riemann_keys/data/english.py
riemann_keys/tests/__init__.py
riemann_keys/tests/bip39_test_vectors.py
riemann_keys/tests/test_bip39.py
riemann_keys/tests/test_hdkey.py
hdkey-0.1.1.dist-info/LICENSE
hdkey-0.1.1.dist-info/METADATA
hdkey-0.1.1.dist-info/WHEEL
hdkey-0.1.1.dist-info/top_level.txt
hdkey-0.1.1.dist-info/RECORD
